{
  "code": "MWAFLE",
  "host": "Heheszek",
  "players": [
    "Heheszek",
    "Wixa"
  ],
  "status": "waiting",
  "settings": {
    "hint_mode": "off",
    "round_limit": 10,
    "selected_categories": [
      "Jedzenie",
      "Zwierzęta"
    ]
  },
  "round": 0,
  "scores": {
    "Heheszek": 0,
    "Wixa": 0
  },
  "submissions": {
    "Heheszek": [],
    "Wixa": []
  },
  "impostor_guess": "",
  "guess_status": "none",
  "votes": {},
  "voted_out": null,
  "round_winner": null,
  "stats": {
    "Heheszek": {
      "times_impostor": 0,
      "impostor_wins": 0,
      "impostor_losses": 0,
      "correct_votes": 0,
      "total_votes_received": 0
    },
    "Wixa": {
      "times_impostor": 0,
      "impostor_wins": 0,
      "impostor_losses": 0,
      "correct_votes": 0,
      "total_votes_received": 0
    }
  }
}